{
  "date": "2026-06-03",
  "items": [
    {
      "symbol": "NVDA",
      "name": "NVIDIA Corporation",
      "score_0_1": 0.322049,
      "points_observed": 93,
      "last_value": 16.0
    },
    {
      "symbol": "MSFT",
      "name": "Microsoft Corporation",
      "score_0_1": 0.307951,
      "points_observed": 93,
      "last_value": 22.0
    },
    {
      "symbol": "PLTR",
      "name": "Palantir Technologies Inc.",
      "score_0_1": 0.30577,
      "points_observed": 93,
      "last_value": 22.0
    },
    {
      "symbol": "AI",
      "name": "C3.ai, Inc.",
      "score_0_1": 0.033136,
      "points_observed": 93,
      "last_value": 46.0
    },
    {
      "symbol": "ISRG",
      "name": "Intuitive Surgical, Inc.",
      "score_0_1": 0.114805,
      "points_observed": 93,
      "last_value": 0.0
    },
    {
      "symbol": "TER",
      "name": "Teradyne, Inc.",
      "score_0_1": 0.018715,
      "points_observed": 93,
      "last_value": 55.0
    },
    {
      "symbol": "SYM",
      "name": "Symbotic Inc.",
      "score_0_1": 0.006758,
      "points_observed": 93,
      "last_value": 0.0
    },
    {
      "symbol": "RKLB",
      "name": "Rocket Lab USA, Inc.",
      "score_0_1": 0.659002,
      "points_observed": 93,
      "last_value": 32.0
    },
    {
      "symbol": "IRDM",
      "name": "Iridium Communications Inc.",
      "score_0_1": 0.496984,
      "points_observed": 93,
      "last_value": 0.0
    },
    {
      "symbol": "VSAT",
      "name": "Viasat, Inc.",
      "score_0_1": 0.178245,
      "points_observed": 93,
      "last_value": 0.0
    },
    {
      "symbol": "INOD",
      "name": "Innodata Inc.",
      "score_0_1": 0.299269,
      "points_observed": 93,
      "last_value": 0.0
    },
    {
      "symbol": "SOUN",
      "name": "SoundHound AI, Inc.",
      "score_0_1": 0.252539,
      "points_observed": 93,
      "last_value": 19.0
    },
    {
      "symbol": "MNDY",
      "name": "Monday.com Ltd.",
      "score_0_1": 0.58815,
      "points_observed": 93,
      "last_value": 0.0
    },
    {
      "symbol": "AVAV",
      "name": "AeroVironment, Inc.",
      "score_0_1": 0.090125,
      "points_observed": 93,
      "last_value": 0.0
    },
    {
      "symbol": "PERF",
      "name": "Perfect Corp.",
      "score_0_1": 0.239838,
      "points_observed": 93,
      "last_value": 40.0
    },
    {
      "symbol": "GDRX",
      "name": "GoodRx Holdings, Inc.",
      "score_0_1": 0.732154,
      "points_observed": 93,
      "last_value": 0.0
    },
    {
      "symbol": "ABCL",
      "name": "AbCellera Biologics Inc.",
      "score_0_1": 0.559456,
      "points_observed": 93,
      "last_value": 0.0
    },
    {
      "symbol": "U",
      "name": "Unity Software Inc.",
      "score_0_1": 0.172543,
      "points_observed": 93,
      "last_value": 81.0
    },
    {
      "symbol": "TEM",
      "name": "Tempus AI, Inc.",
      "score_0_1": 0.028691,
      "points_observed": 93,
      "last_value": 58.0
    },
    {
      "symbol": "VRT",
      "name": "Vertiv Holdings Co",
      "score_0_1": 0.324365,
      "points_observed": 93,
      "last_value": 40.0
    },
    {
      "symbol": "OII",
      "name": "Oceaneering International Inc.",
      "score_0_1": 0.593774,
      "points_observed": 93,
      "last_value": 0.0
    },
    {
      "symbol": "CGNX",
      "name": "Cognex Corporation",
      "score_0_1": 0.684874,
      "points_observed": 93,
      "last_value": 0.0
    },
    {
      "symbol": "KTOS",
      "name": "Kratos Defense & Security Solutions Inc.",
      "score_0_1": 0.067204,
      "points_observed": 93,
      "last_value": 0.0
    },
    {
      "symbol": "OUST",
      "name": "Ouster Inc.",
      "score_0_1": 0.045708,
      "points_observed": 93,
      "last_value": 0.0
    },
    {
      "symbol": "FTI",
      "name": "TechnipFMC plc",
      "score_0_1": 0.011842,
      "points_observed": 93,
      "last_value": 0.0
    },
    {
      "symbol": "LNG",
      "name": "Cheniere Energy Inc.",
      "score_0_1": 0.095586,
      "points_observed": 93,
      "last_value": 8.0
    },
    {
      "symbol": "PR",
      "name": "Permian Resources Corporation",
      "score_0_1": 0.050518,
      "points_observed": 93,
      "last_value": 53.0
    },
    {
      "symbol": "MTDR",
      "name": "Matador Resources Company",
      "score_0_1": 0.711862,
      "points_observed": 93,
      "last_value": 0.0
    },
    {
      "symbol": "ROK",
      "name": "Rockwell Automation Inc.",
      "score_0_1": 0.036605,
      "points_observed": 93,
      "last_value": 61.0
    },
    {
      "symbol": "IONQ",
      "name": "IonQ Inc.",
      "score_0_1": 0.453564,
      "points_observed": 93,
      "last_value": 26.0
    },
    {
      "symbol": "OXY",
      "name": "Occidental Petroleum Corporation",
      "score_0_1": 0.075047,
      "points_observed": 93,
      "last_value": 51.0
    },
    {
      "symbol": "RCAT",
      "name": "Red Cat Holdings Inc.",
      "score_0_1": 0.091187,
      "points_observed": 93,
      "last_value": 0.0
    },
    {
      "symbol": "HIMS",
      "name": "Hims & Hers Health Inc.",
      "score_0_1": 0.060872,
      "points_observed": 93,
      "last_value": 22.0
    },
    {
      "symbol": "RBRK",
      "name": "Rubrik Inc.",
      "score_0_1": 0.247267,
      "points_observed": 93,
      "last_value": 0.0
    },
    {
      "symbol": "CRDO",
      "name": "Credo Technology Group Holding Ltd",
      "score_0_1": 0.729824,
      "points_observed": 93,
      "last_value": 32.0
    },
    {
      "symbol": "ALAB",
      "name": "Astera Labs Inc.",
      "score_0_1": 0.905856,
      "points_observed": 93,
      "last_value": 62.0
    },
    {
      "symbol": "SERV",
      "name": "Serve Robotics Inc.",
      "score_0_1": 0.345047,
      "points_observed": 93,
      "last_value": 57.0
    },
    {
      "symbol": "PDYN",
      "name": "Palladyne AI Corp.",
      "score_0_1": 0.574931,
      "points_observed": 93,
      "last_value": 0.0
    },
    {
      "symbol": "AEVA",
      "name": "Aeva Technologies Inc.",
      "score_0_1": 0.0,
      "points_observed": 0,
      "last_value": null
    },
    {
      "symbol": "PRCT",
      "name": "PROCEPT BioRobotics Corporation",
      "score_0_1": 0.0,
      "points_observed": 0,
      "last_value": null
    },
    {
      "symbol": "LUNR",
      "name": "Intuitive Machines Inc.",
      "score_0_1": 0.0,
      "points_observed": 0,
      "last_value": null
    },
    {
      "symbol": "ASTS",
      "name": "AST SpaceMobile Inc.",
      "score_0_1": 0.0,
      "points_observed": 0,
      "last_value": null
    },
    {
      "symbol": "NBIS",
      "name": "Nebius Group N.V.",
      "score_0_1": 0.0,
      "points_observed": 0,
      "last_value": null
    },
    {
      "symbol": "S",
      "name": "SentinelOne Inc.",
      "score_0_1": 0.0,
      "points_observed": 0,
      "last_value": null
    },
    {
      "symbol": "ESTC",
      "name": "Elastic N.V.",
      "score_0_1": 0.0,
      "points_observed": 0,
      "last_value": null
    },
    {
      "symbol": "RXRX",
      "name": "Recursion Pharmaceuticals Inc.",
      "score_0_1": 0.0,
      "points_observed": 0,
      "last_value": null
    },
    {
      "symbol": "TMDX",
      "name": "TransMedics Group Inc.",
      "score_0_1": 0.0,
      "points_observed": 0,
      "last_value": null
    }
  ]
}