[
  {
    "symbol": "AI",
    "name": "C3.ai, Inc.",
    "theme": "AI",
    "pct_change": 0.009613751302722453,
    "vol_ratio": 0.04450526415882711,
    "news_count": 0,
    "eligible_liquidity": true,
    "score_components": {
      "vol_anomaly": 0.21232000532036716,
      "insider_momo": null
    },
    "score_weights": {
      "vol_anomaly": 0.6,
      "insider_momo": 0.4
    },
    "final_score_0_1": 0.21232000532036716,
    "score_pts": 212,
    "vol_anomaly_score": 0.21232000532036716,
    "insider_momo": null,
    "chart_url": "/charts/2025-08-25/AI.png",
    "tech_note": "Auto tech note TBD",
    "ir_note": "IR/News summary TBD",
    "detail": {
      "vol_anomaly": {
        "score_0_1": 0.21232000532036716,
        "rvol20": 0.04450526415882711,
        "z60": -0.8870548663547547,
        "pct_rank_90": 0.011111111111111112,
        "z_norm": 0.4112945133645245,
        "rvol_norm": 0.014835088052942369,
        "dollar_vol": 8261444.71113205,
        "eligible": true,
        "today_volume": 478805.0,
        "sma20_volume": 10758390.25,
        "close": 17.25429916381836
      }
    },
    "rank": 1
  },
  {
    "symbol": "VSAT",
    "name": "Viasat, Inc.",
    "theme": "Space",
    "pct_change": 0.04643748372229003,
    "vol_ratio": 0.1278309966676799,
    "news_count": 0,
    "eligible_liquidity": true,
    "score_components": {
      "vol_anomaly": 0.20752213923272034,
      "insider_momo": null
    },
    "score_weights": {
      "vol_anomaly": 0.6,
      "insider_momo": 0.4
    },
    "final_score_0_1": 0.20752213923272034,
    "score_pts": 208,
    "vol_anomaly_score": 0.20752213923272034,
    "insider_momo": null,
    "chart_url": "/charts/2025-08-25/VSAT.png",
    "tech_note": "Auto tech note TBD",
    "ir_note": "IR/News summary TBD",
    "detail": {
      "vol_anomaly": {
        "score_0_1": 0.20752213923272034,
        "rvol20": 0.1278309966676799,
        "z60": -1.1496636531253972,
        "pct_rank_90": 0.011111111111111112,
        "z_norm": 0.38503363468746027,
        "rvol_norm": 0.04261033222255997,
        "dollar_vol": 17964130.598567963,
        "eligible": true,
        "today_volume": 608541.0,
        "sma20_volume": 4760512.05,
        "close": 29.520000457763672
      }
    },
    "rank": 2
  },
  {
    "symbol": "SOUN",
    "name": "SoundHound AI, Inc.",
    "theme": "AI",
    "pct_change": 0.03035511572259338,
    "vol_ratio": 0.08642649601773207,
    "news_count": 0,
    "eligible_liquidity": true,
    "score_components": {
      "vol_anomaly": 0.19319880893138802,
      "insider_momo": null
    },
    "score_weights": {
      "vol_anomaly": 0.6,
      "insider_momo": 0.4
    },
    "final_score_0_1": 0.19319880893138802,
    "score_pts": 193,
    "vol_anomaly_score": 0.19319880893138802,
    "insider_momo": null,
    "chart_url": "/charts/2025-08-25/SOUN.png",
    "tech_note": "Auto tech note TBD",
    "ir_note": "IR/News summary TBD",
    "detail": {
      "vol_anomaly": {
        "score_0_1": 0.19319880893138802,
        "rvol20": 0.08642649601773207,
        "z60": -1.3533212578521479,
        "pct_rank_90": 0.011111111111111112,
        "z_norm": 0.3646678742147852,
        "rvol_norm": 0.02880883200591069,
        "dollar_vol": 55191457.288757324,
        "eligible": true,
        "today_volume": 4423243.0,
        "sma20_volume": 51179247.15,
        "close": 12.47760009765625
      }
    },
    "rank": 3
  },
  {
    "symbol": "RKLB",
    "name": "Rocket Lab USA, Inc.",
    "theme": "Space",
    "pct_change": 0.027107131431747457,
    "vol_ratio": 0.18118594874838262,
    "news_count": 0,
    "eligible_liquidity": true,
    "score_components": {
      "vol_anomaly": 0.19071907566360086,
      "insider_momo": null
    },
    "score_weights": {
      "vol_anomaly": 0.6,
      "insider_momo": 0.4
    },
    "final_score_0_1": 0.19071907566360086,
    "score_pts": 191,
    "vol_anomaly_score": 0.19071907566360086,
    "insider_momo": null,
    "chart_url": "/charts/2025-08-25/RKLB.png",
    "tech_note": "Auto tech note TBD",
    "ir_note": "IR/News summary TBD",
    "detail": {
      "vol_anomaly": {
        "score_0_1": 0.19071907566360086,
        "rvol20": 0.18118594874838262,
        "z60": -1.5924348286691923,
        "pct_rank_90": 0.011111111111111112,
        "z_norm": 0.34075651713308075,
        "rvol_norm": 0.06039531624946087,
        "dollar_vol": 159715301.5,
        "eligible": true,
        "today_volume": 3293099.0,
        "sma20_volume": 18175244.95,
        "close": 48.5
      }
    },
    "rank": 4
  },
  {
    "symbol": "U",
    "name": "Unity",
    "theme": "AI",
    "pct_change": 0.002008486384126876,
    "vol_ratio": 0.08445658868639704,
    "news_count": 0,
    "eligible_liquidity": true,
    "score_components": {
      "vol_anomaly": 0.1894729056017172,
      "insider_momo": null
    },
    "score_weights": {
      "vol_anomaly": 0.6,
      "insider_momo": 0.4
    },
    "final_score_0_1": 0.1894729056017172,
    "score_pts": 189,
    "vol_anomaly_score": 0.1894729056017172,
    "insider_momo": null,
    "chart_url": "/charts/2025-08-25/U.png",
    "tech_note": "Auto tech note TBD",
    "ir_note": "IR/News summary TBD",
    "detail": {
      "vol_anomaly": {
        "score_0_1": 0.1894729056017172,
        "rvol20": 0.08445658868639704,
        "z60": -1.4238995097828941,
        "pct_rank_90": 0.011111111111111112,
        "z_norm": 0.35761004902171056,
        "rvol_norm": 0.028152196228799012,
        "dollar_vol": 48177037.03580475,
        "eligible": true,
        "today_volume": 1207142.0,
        "sma20_volume": 14293047.1,
        "close": 39.90999984741211
      }
    },
    "rank": 5
  },
  {
    "symbol": "PLTR",
    "name": "Palantir Technologies Inc.",
    "theme": "AI",
    "pct_change": -0.0030858345485900254,
    "vol_ratio": 0.0968418660843313,
    "news_count": 0,
    "eligible_liquidity": true,
    "score_components": {
      "vol_anomaly": 0.165094683071213,
      "insider_momo": null
    },
    "score_weights": {
      "vol_anomaly": 0.6,
      "insider_momo": 0.4
    },
    "final_score_0_1": 0.165094683071213,
    "score_pts": 165,
    "vol_anomaly_score": 0.165094683071213,
    "insider_momo": null,
    "chart_url": "/charts/2025-08-25/PLTR.png",
    "tech_note": "Auto tech note TBD",
    "ir_note": "IR/News summary TBD",
    "detail": {
      "vol_anomaly": {
        "score_0_1": 0.165094683071213,
        "rvol20": 0.0968418660843313,
        "z60": -1.9362345151888465,
        "pct_rank_90": 0.011111111111111112,
        "z_norm": 0.30637654848111534,
        "rvol_norm": 0.03228062202811043,
        "dollar_vol": 1194514558.6525269,
        "eligible": true,
        "today_volume": 7623669.0,
        "sma20_volume": 78722863.45,
        "close": 156.68499755859375
      }
    },
    "rank": 6
  },
  {
    "symbol": "VRT",
    "name": "Vertiv Holdings Co",
    "theme": "AI",
    "pct_change": 0.011238253450787689,
    "vol_ratio": 0.04178280465206595,
    "news_count": 0,
    "eligible_liquidity": true,
    "score_components": {
      "vol_anomaly": 0.15888433352777614,
      "insider_momo": null
    },
    "score_weights": {
      "vol_anomaly": 0.6,
      "insider_momo": 0.4
    },
    "final_score_0_1": 0.15888433352777614,
    "score_pts": 159,
    "vol_anomaly_score": 0.15888433352777614,
    "insider_momo": null,
    "chart_url": "/charts/2025-08-25/VRT.png",
    "tech_note": "Auto tech note TBD",
    "ir_note": "IR/News summary TBD",
    "detail": {
      "vol_anomaly": {
        "score_0_1": 0.15888433352777614,
        "rvol20": 0.04178280465206595,
        "z60": -1.9503233831930533,
        "pct_rank_90": 0.011111111111111112,
        "z_norm": 0.30496766168069467,
        "rvol_norm": 0.01392760155068865,
        "dollar_vol": 35140461.72325134,
        "eligible": true,
        "today_volume": 277955.0,
        "sma20_volume": 6652377.75,
        "close": 126.42500305175781
      }
    },
    "rank": 7
  },
  {
    "symbol": "TEM",
    "name": "Tempus",
    "theme": "AI",
    "pct_change": -0.003952609298110795,
    "vol_ratio": 0.1001605302922363,
    "news_count": 0,
    "eligible_liquidity": true,
    "score_components": {
      "vol_anomaly": 0.1571124095186044,
      "insider_momo": null
    },
    "score_weights": {
      "vol_anomaly": 0.6,
      "insider_momo": 0.4
    },
    "final_score_0_1": 0.1571124095186044,
    "score_pts": 157,
    "vol_anomaly_score": 0.1571124095186044,
    "insider_momo": null,
    "chart_url": "/charts/2025-08-25/TEM.png",
    "tech_note": "Auto tech note TBD",
    "ir_note": "IR/News summary TBD",
    "detail": {
      "vol_anomaly": {
        "score_0_1": 0.1571124095186044,
        "rvol20": 0.1001605302922363,
        "z60": -2.1025173146568283,
        "pct_rank_90": 0.011111111111111112,
        "z_norm": 0.2897482685343171,
        "rvol_norm": 0.03338684343074543,
        "dollar_vol": 89737878.588768,
        "eligible": true,
        "today_volume": 1187009.0,
        "sma20_volume": 11851065.45,
        "close": 75.5999984741211
      }
    },
    "rank": 8
  },
  {
    "symbol": "MSFT",
    "name": "Microsoft Corporation",
    "theme": "AI",
    "pct_change": -0.0011303837567521637,
    "vol_ratio": 0.06328428071394487,
    "news_count": 0,
    "eligible_liquidity": true,
    "score_components": {
      "vol_anomaly": 0.12239952781850921,
      "insider_momo": null
    },
    "score_weights": {
      "vol_anomaly": 0.6,
      "insider_momo": 0.4
    },
    "final_score_0_1": 0.12239952781850921,
    "score_pts": 122,
    "vol_anomaly_score": 0.12239952781850921,
    "insider_momo": null,
    "chart_url": "/charts/2025-08-25/MSFT.png",
    "tech_note": "Auto tech note TBD",
    "ir_note": "IR/News summary TBD",
    "detail": {
      "vol_anomaly": {
        "score_0_1": 0.12239952781850921,
        "rvol20": 0.06328428071394487,
        "z60": -2.7230224495021496,
        "pct_rank_90": 0.011111111111111112,
        "z_norm": 0.227697755049785,
        "rvol_norm": 0.021094760237981625,
        "dollar_vol": 712729412.4946289,
        "eligible": true,
        "today_volume": 1415016.0,
        "sma20_volume": 22359675.8,
        "close": 503.69000244140625
      }
    },
    "rank": 9
  },
  {
    "symbol": "NVDA",
    "name": "NVIDIA Corporation",
    "theme": "AI",
    "pct_change": -0.002141118469847492,
    "vol_ratio": 0.11582956627362109,
    "news_count": 0,
    "eligible_liquidity": true,
    "score_components": {
      "vol_anomaly": 0.06927878321742832,
      "insider_momo": null
    },
    "score_weights": {
      "vol_anomaly": 0.6,
      "insider_momo": 0.4
    },
    "final_score_0_1": 0.06927878321742832,
    "score_pts": 69,
    "vol_anomaly_score": 0.06927878321742832,
    "insider_momo": null,
    "chart_url": "/charts/2025-08-25/NVDA.png",
    "tech_note": "Auto tech note TBD",
    "ir_note": "IR/News summary TBD",
    "detail": {
      "vol_anomaly": {
        "score_0_1": 0.06927878321742832,
        "rvol20": 0.11582956627362109,
        "z60": -3.8905279126431203,
        "pct_rank_90": 0.011111111111111112,
        "z_norm": 0.11094720873568797,
        "rvol_norm": 0.03860985542454037,
        "dollar_vol": 3214101981.2921906,
        "eligible": true,
        "today_volume": 17913345.0,
        "sma20_volume": 154652612.25,
        "close": 179.4250030517578
      }
    },
    "rank": 10
  }
]