{
  "items": {
    "NVDA": {
      "score_0_1": 0.5791483333333334,
      "recent_count": 60
    },
    "MSFT": {
      "score_0_1": 0.5649707547169811,
      "recent_count": 53
    },
    "PLTR": {
      "score_0_1": 0.5368870689655172,
      "recent_count": 58
    },
    "AI": {
      "score_0_1": 0.48624576271186437,
      "recent_count": 59
    },
    "ISRG": {
      "score_0_1": 0.5571872881355933,
      "recent_count": 59
    },
    "TER": {
      "score_0_1": 0.5576560975609756,
      "recent_count": 41
    },
    "SYM": {
      "score_0_1": 0.5623530612244898,
      "recent_count": 49
    },
    "RKLB": {
      "score_0_1": 0.5940258620689655,
      "recent_count": 58
    },
    "IRDM": {
      "score_0_1": 0.596354,
      "recent_count": 50
    },
    "VSAT": {
      "score_0_1": 0.5807456140350877,
      "recent_count": 57
    },
    "INOD": {
      "score_0_1": 0.5854154545454545,
      "recent_count": 55
    },
    "SOUN": {
      "score_0_1": 0.5737116666666666,
      "recent_count": 60
    },
    "MNDY": {
      "score_0_1": 0.5711225,
      "recent_count": 60
    },
    "AVAV": {
      "score_0_1": 0.5581103773584906,
      "recent_count": 53
    },
    "PERF": {
      "score_0_1": 0.8003336206896551,
      "recent_count": 58
    },
    "GDRX": {
      "score_0_1": 0.628393220338983,
      "recent_count": 59
    },
    "ABCL": {
      "score_0_1": 0.604334090909091,
      "recent_count": 44
    },
    "U": {
      "score_0_1": 0.6019401785714286,
      "recent_count": 56
    },
    "TEM": {
      "score_0_1": 0.5791016666666666,
      "recent_count": 60
    },
    "VRT": {
      "score_0_1": 0.5868758333333333,
      "recent_count": 60
    }
  },
  "date": "2025-08-29",
  "lookback_days": 31
}