{
  "items": [
    {
      "id": "2026-05-06_SYM",
      "signal_date": "2026-05-06",
      "symbol": "SYM",
      "name": "Symbotic Inc.",
      "rank": 1,
      "rank_bucket": "#1",
      "score_bucket": "850+",
      "profile": "Volume + Compression + Trends + News",
      "score_pts": 851,
      "final_score_0_1": 0.850761,
      "volume_anomaly": 0.824686,
      "compression_release": 0.772727,
      "trends_breakout": 0.97709,
      "news": 0.807759,
      "policy_version": "legacy_top3",
      "signal_eligible": true,
      "eligibility_rule": "legacy_score_750+",
      "signal_quality": "Strong Signal",
      "entry_date": "2026-05-07",
      "entry_price": 57.272,
      "gap_pct": -6.36,
      "return_1w_pct": null,
      "return_1m_pct": null,
      "return_3m_pct": null,
      "current_return_pct": -1.47,
      "current_close": 56.43,
      "current_date": "2026-05-07",
      "max_gain_since_entry_pct": 7.19,
      "max_drawdown_since_entry_pct": -3.91,
      "status": "active",
      "d5_return_pct": null,
      "d10_return_pct": null,
      "d20_return_pct": null,
      "max_gain_20d_pct": 7.19,
      "max_drawdown_20d_pct": -3.91
    },
    {
      "id": "2026-05-05_VRT",
      "signal_date": "2026-05-05",
      "symbol": "VRT",
      "name": "Vertiv Holdings Co",
      "rank": 2,
      "rank_bucket": "#2-3",
      "score_bucket": "750-799",
      "profile": "Compression + Trends",
      "score_pts": 781,
      "final_score_0_1": 0.78084,
      "volume_anomaly": 0.682903,
      "compression_release": 0.928571,
      "trends_breakout": 0.900064,
      "news": 0.710088,
      "policy_version": "legacy_top3",
      "signal_eligible": true,
      "eligibility_rule": "legacy_score_750+",
      "signal_quality": "Signal",
      "entry_date": "2026-05-06",
      "entry_price": 351.56,
      "gap_pct": 3.09,
      "return_1w_pct": null,
      "return_1m_pct": null,
      "return_3m_pct": null,
      "current_return_pct": -3.29,
      "current_close": 340.01,
      "current_date": "2026-05-07",
      "max_gain_since_entry_pct": 2.36,
      "max_drawdown_since_entry_pct": -4.37,
      "status": "active",
      "d5_return_pct": null,
      "d10_return_pct": null,
      "d20_return_pct": null,
      "max_gain_20d_pct": 2.36,
      "max_drawdown_20d_pct": -4.37
    },
    {
      "id": "2026-05-05_OUST",
      "signal_date": "2026-05-05",
      "symbol": "OUST",
      "name": "Ouster Inc.",
      "rank": 1,
      "rank_bucket": "#1",
      "score_bucket": "850+",
      "profile": "Volume + Trends + News",
      "score_pts": 869,
      "final_score_0_1": 0.868522,
      "volume_anomaly": 0.871086,
      "compression_release": 0.607143,
      "trends_breakout": 0.999958,
      "news": 0.890323,
      "policy_version": "legacy_top3",
      "signal_eligible": true,
      "eligibility_rule": "legacy_score_750+",
      "signal_quality": "Strong Signal",
      "entry_date": "2026-05-06",
      "entry_price": 26.5,
      "gap_pct": -7.34,
      "return_1w_pct": null,
      "return_1m_pct": null,
      "return_3m_pct": null,
      "current_return_pct": -7.51,
      "current_close": 24.51,
      "current_date": "2026-05-07",
      "max_gain_since_entry_pct": 11.96,
      "max_drawdown_since_entry_pct": -8.53,
      "status": "active",
      "d5_return_pct": null,
      "d10_return_pct": null,
      "d20_return_pct": null,
      "max_gain_20d_pct": 11.96,
      "max_drawdown_20d_pct": -8.53
    },
    {
      "id": "2026-05-01_SOUN",
      "signal_date": "2026-05-01",
      "symbol": "SOUN",
      "name": "SoundHound AI, Inc.",
      "rank": 1,
      "rank_bucket": "#1",
      "score_bucket": "750-799",
      "profile": "Volume + Trends + News",
      "score_pts": 785,
      "final_score_0_1": 0.78527,
      "volume_anomaly": 0.897862,
      "compression_release": 0.466667,
      "trends_breakout": 0.833905,
      "news": 0.77017,
      "policy_version": "legacy_top3",
      "signal_eligible": true,
      "eligibility_rule": "legacy_score_750+",
      "signal_quality": "Signal",
      "entry_date": "2026-05-04",
      "entry_price": 9.545,
      "gap_pct": -0.16,
      "return_1w_pct": null,
      "return_1m_pct": null,
      "return_3m_pct": null,
      "current_return_pct": 0.89,
      "current_close": 9.63,
      "current_date": "2026-05-07",
      "max_gain_since_entry_pct": 5.24,
      "max_drawdown_since_entry_pct": -6.6,
      "status": "active",
      "d5_return_pct": null,
      "d10_return_pct": null,
      "d20_return_pct": null,
      "max_gain_20d_pct": 5.24,
      "max_drawdown_20d_pct": -6.6
    },
    {
      "id": "2026-04-29_MSFT",
      "signal_date": "2026-04-29",
      "symbol": "MSFT",
      "name": "Microsoft Corporation",
      "rank": 1,
      "rank_bucket": "#1",
      "score_bucket": "750-799",
      "profile": "Trends + News",
      "score_pts": 773,
      "final_score_0_1": 0.773131,
      "volume_anomaly": 0.481276,
      "compression_release": 0.7,
      "trends_breakout": 0.998736,
      "news": 1.0,
      "policy_version": "legacy_top3",
      "signal_eligible": true,
      "eligibility_rule": "legacy_score_750+",
      "signal_quality": "Signal",
      "entry_date": "2026-04-30",
      "entry_price": 410.7875,
      "gap_pct": -3.22,
      "return_1w_pct": 2.43,
      "return_1m_pct": null,
      "return_3m_pct": null,
      "current_return_pct": 2.43,
      "current_close": 420.77,
      "current_date": "2026-05-07",
      "max_gain_since_entry_pct": 4.19,
      "max_drawdown_since_entry_pct": -3.11,
      "status": "completed_1w",
      "d5_return_pct": 2.43,
      "d10_return_pct": null,
      "d20_return_pct": null,
      "max_gain_20d_pct": 4.19,
      "max_drawdown_20d_pct": -3.11
    },
    {
      "id": "2026-04-27_NVDA",
      "signal_date": "2026-04-27",
      "symbol": "NVDA",
      "name": "NVIDIA Corporation",
      "rank": 1,
      "rank_bucket": "#1",
      "score_bucket": "750-799",
      "profile": "News",
      "score_pts": 752,
      "final_score_0_1": 0.75165,
      "volume_anomaly": 0.749749,
      "compression_release": 0.633333,
      "trends_breakout": 0.576952,
      "news": 1.0,
      "policy_version": "legacy_top3",
      "signal_eligible": true,
      "eligibility_rule": "legacy_score_750+",
      "signal_quality": "Signal",
      "entry_date": "2026-04-28",
      "entry_price": 209.505,
      "gap_pct": -3.28,
      "return_1w_pct": -6.21,
      "return_1m_pct": null,
      "return_3m_pct": null,
      "current_return_pct": 0.95,
      "current_close": 211.5,
      "current_date": "2026-05-07",
      "max_gain_since_entry_pct": 2.49,
      "max_drawdown_since_entry_pct": -7.05,
      "status": "completed_1w",
      "d5_return_pct": -6.21,
      "d10_return_pct": null,
      "d20_return_pct": null,
      "max_gain_20d_pct": 2.49,
      "max_drawdown_20d_pct": -7.05
    },
    {
      "id": "2026-04-23_VRT",
      "signal_date": "2026-04-23",
      "symbol": "VRT",
      "name": "Vertiv Holdings Co",
      "rank": 1,
      "rank_bucket": "#1",
      "score_bucket": "750-799",
      "profile": "Compression + News",
      "score_pts": 750,
      "final_score_0_1": 0.74975,
      "volume_anomaly": 0.628438,
      "compression_release": 0.962963,
      "trends_breakout": 0.678505,
      "news": 0.862903,
      "policy_version": "legacy_top3",
      "signal_eligible": true,
      "eligibility_rule": "legacy_score_750+",
      "signal_quality": "Signal",
      "entry_date": "2026-04-24",
      "entry_price": 328.0,
      "gap_pct": 1.94,
      "return_1w_pct": 0.09,
      "return_1m_pct": null,
      "return_3m_pct": null,
      "current_return_pct": 3.66,
      "current_close": 340.01,
      "current_date": "2026-05-07",
      "max_gain_since_entry_pct": 9.71,
      "max_drawdown_since_entry_pct": -10.4,
      "status": "completed_1w",
      "d5_return_pct": 0.09,
      "d10_return_pct": null,
      "d20_return_pct": null,
      "max_gain_20d_pct": 9.71,
      "max_drawdown_20d_pct": -10.4
    }
  ]
}